[
  {
    "description": "Review tools directory content/design before launch\n",
    "user_generated": false,
    "completed": false,
    "recording_timestamp": "00:05:49",
    "recording_playback_url": "https://fathom.video/calls/177022572?timestamp=349.9999",
    "assignee": {
      "name": "Nav Singh",
      "email": "nav@heygen.com",
      "team": null
    }
  },
  {
    "description": "Review/feedback on Airtable content to unblock production\n",
    "user_generated": false,
    "completed": false,
    "recording_timestamp": "00:08:14",
    "recording_playback_url": "https://fathom.video/calls/177022572?timestamp=494.9999",
    "assignee": {
      "name": "Nav Singh",
      "email": "nav@heygen.com",
      "team": null
    }
  },
  {
    "description": "Set up Airtable-Webflow sync for content management\n",
    "user_generated": false,
    "completed": false,
    "recording_timestamp": "00:11:54",
    "recording_playback_url": "https://fathom.video/calls/177022572?timestamp=714.9999",
    "assignee": {
      "name": "Jimmy Pal",
      "email": "sadira@growthxlabs.com",
      "team": null
    }
  },
  {
    "description": "Add staging link column in Airtable for easier content review\n",
    "user_generated": false,
    "completed": false,
    "recording_timestamp": "00:16:06",
    "recording_playback_url": "https://fathom.video/calls/177022572?timestamp=966.9999",
    "assignee": {
      "name": "Bisera Stankovska",
      "email": "bisera@growthxlabs.com",
      "team": "GrowthX Team"
    }
  },
  {
    "description": "Add \"initiative\" column in Airtable for e-learning/marketing campaign categorization\n",
    "user_generated": false,
    "completed": false,
    "recording_timestamp": "00:16:29",
    "recording_playback_url": "https://fathom.video/calls/177022572?timestamp=989.9999",
    "assignee": {
      "name": "Holly Xiao",
      "email": null,
      "team": null
    }
  },
  {
    "description": "Publish ready marketing blog posts in Webflow\n",
    "user_generated": false,
    "completed": false,
    "recording_timestamp": "00:21:38",
    "recording_playback_url": "https://fathom.video/calls/177022572?timestamp=1298.9999",
    "assignee": {
      "name": "Holly Xiao",
      "email": null,
      "team": null
    }
  }
]