{
    "title": "Metronome <> Growth X - Weekly Sync",
    "meeting_title": "Metronome <> Growth X - Weekly Sync",
    "url": "https://fathom.video/calls/521647680",
    "created_at": "2026-01-06T19:22:24Z",
    "scheduled_start_time": "2026-01-06T19:00:00Z",
    "scheduled_end_time": "2026-01-06T19:30:00Z",
    "recording_id": 112183436,
    "recording_start_time": "2026-01-06T18:59:52Z",
    "recording_end_time": "2026-01-06T19:22:18Z",
    "calendar_invitees_domains_type": "one_or_more_external",
    "transcript": [
        {
            "speaker": {
                "display_name": "Katya Luscomb",
                "matched_calendar_invitee_email": "katya@growthx.ai"
            },
            "text": "Hey, Will.",
            "timestamp": "00:02:02"
        },
        {
            "speaker": {
                "display_name": "Will Watters",
                "matched_calendar_invitee_email": "will.watters@metronome.com"
            },
            "text": "Hey, sorry I'm late.",
            "timestamp": "00:02:06"
        },
        {
            "speaker": {
                "display_name": "Katya Luscomb",
                "matched_calendar_invitee_email": "katya@growthx.ai"
            },
            "text": "No worries.",
            "timestamp": "00:02:08"
        },
        {
            "speaker": {
                "display_name": "Katya Luscomb",
                "matched_calendar_invitee_email": "katya@growthx.ai"
            },
            "text": "It's, you know, first Tuesday of the year.",
            "timestamp": "00:02:09"
        },
        {
            "speaker": {
                "display_name": "Katya Luscomb",
                "matched_calendar_invitee_email": "katya@growthx.ai"
            },
            "text": "I think there's a lot of us probably getting our heads back on from the holidays.",
            "timestamp": "00:02:11"
        },
        {
            "speaker": {
                "display_name": "Will Watters",
                "matched_calendar_invitee_email": "will.watters@metronome.com"
            },
            "text": "Yeah, yeah, absolutely.",
            "timestamp": "00:02:17"
        },
        {
            "speaker": {
                "display_name": "Katya Luscomb",
                "matched_calendar_invitee_email": "katya@growthx.ai"
            },
            "text": "Did you have a good break?",
            "timestamp": "00:02:19"
        },
        {
            "speaker": {
                "display_name": "Will Watters",
                "matched_calendar_invitee_email": "will.watters@metronome.com"
            },
            "text": "Did you take a break at all?",
            "timestamp": "00:02:21"
        },
        {
            "speaker": {
                "display_name": "Will Watters",
                "matched_calendar_invitee_email": "will.watters@metronome.com"
            },
            "text": "Yeah, it was great.",
            "timestamp": "00:02:22"
        },
        {
            "speaker": {
                "display_name": "Will Watters",
                "matched_calendar_invitee_email": "will.watters@metronome.com"
            },
            "text": "Definitely took a couple days off.",
            "timestamp": "00:02:24"
        },
        {
            "speaker": {
                "display_name": "Will Watters",
                "matched_calendar_invitee_email": "will.watters@metronome.com"
            },
            "text": "We just kind of hung out here in Chicago.",
            "timestamp": "00:02:26"
        },
        {
            "speaker": {
                "display_name": "Will Watters",
                "matched_calendar_invitee_email": "will.watters@metronome.com"
            },
            "text": "I've had a pretty busy year.",
            "timestamp": "00:02:30"
        },
        {
            "speaker": {
                "display_name": "Will Watters",
                "matched_calendar_invitee_email": "will.watters@metronome.com"
            },
            "text": "My wife has also been traveling a good amount recently.",
            "timestamp": "00:02:32"
        },
        {
            "speaker": {
                "display_name": "Will Watters",
                "matched_calendar_invitee_email": "will.watters@metronome.com"
            },
            "text": "So we just decided to kind of hang out, which was great.",
            "timestamp": "00:02:36"
        },
        {
            "speaker": {
                "display_name": "Katya Luscomb",
                "matched_calendar_invitee_email": "katya@growthx.ai"
            },
            "text": "Very relaxing.",
            "timestamp": "00:02:39"
        },
        {
            "speaker": {
                "display_name": "Katya Luscomb",
                "matched_calendar_invitee_email": "katya@growthx.ai"
            },
            "text": "Nice.",
            "timestamp": "00:02:41"
        },
        {
            "speaker": {
                "display_name": "Katya Luscomb",
                "matched_calendar_invitee_email": "katya@growthx.ai"
            },
            "text": "Yeah.",
            "timestamp": "00:02:41"
        },
        {
            "speaker": {
                "display_name": "Katya Luscomb",
                "matched_calendar_invitee_email": "katya@growthx.ai"
            },
            "text": "My husband and I had a blissfully boring holiday a couple of weeks too, which sometimes you just, you need downtime after, yeah, crazy life.",
            "timestamp": "00:02:42"
        },
        {
            "speaker": {
                "display_name": "Will Watters",
                "matched_calendar_invitee_email": "will.watters@metronome.com"
            },
            "text": "Totally.",
            "timestamp": "00:02:51"
        },
        {
            "speaker": {
                "display_name": "Will Watters",
                "matched_calendar_invitee_email": "will.watters@metronome.com"
            },
            "text": "Yeah, it was, yeah, it was nice.",
            "timestamp": "00:02:52"
        },
        {
            "speaker": {
                "display_name": "Katya Luscomb",
                "matched_calendar_invitee_email": "katya@growthx.ai"
            },
            "text": "Cool.",
            "timestamp": "00:02:55"
        },
        {
            "speaker": {
                "display_name": "Katya Luscomb",
                "matched_calendar_invitee_email": "katya@growthx.ai"
            },
            "text": "Good to hear.",
            "timestamp": "00:02:55"
        },
        {
            "speaker": {
                "display_name": "Katya Luscomb",
                "matched_calendar_invitee_email": "katya@growthx.ai"
            },
            "text": "I",
            "timestamp": "00:02:58"
        },
        {
            "speaker": {
                "display_name": "Katya Luscomb",
                "matched_calendar_invitee_email": "katya@growthx.ai"
            },
            "text": "Don't know if you had much chance to like go through all of the agenda.",
            "timestamp": "00:03:00"
        },
        {
            "speaker": {
                "display_name": "Katya Luscomb",
                "matched_calendar_invitee_email": "katya@growthx.ai"
            },
            "text": "There's a lot in here, but I think it's going to be pretty quick overall.",
            "timestamp": "00:03:02"
        },
        {
            "speaker": {
                "display_name": "Katya Luscomb",
                "matched_calendar_invitee_email": "katya@growthx.ai"
            },
            "text": "Just a few things that I wanted to flag.",
            "timestamp": "00:03:07"
        },
        {
            "speaker": {
                "display_name": "Katya Luscomb",
                "matched_calendar_invitee_email": "katya@growthx.ai"
            },
            "text": "Primarily looking ahead at my calendar and like aligning on our meeting schedule.",
            "timestamp": "00:03:10"
        },
        {
            "speaker": {
                "display_name": "Katya Luscomb",
                "matched_calendar_invitee_email": "katya@growthx.ai"
            },
            "text": "I wanted to meet this week since we had a couple of weeks post-holidays where we didn't chat.",
            "timestamp": "00:03:17"
        },
        {
            "speaker": {
                "display_name": "Katya Luscomb",
                "matched_calendar_invitee_email": "katya@growthx.ai"
            },
            "text": "And then starting next week, we'll meet and then move into that bi-weekly schedule, if that works for you guys.",
            "timestamp": "00:03:21"
        },
        {
            "speaker": {
                "display_name": "Will Watters",
                "matched_calendar_invitee_email": "will.watters@metronome.com"
            },
            "text": "Yeah, I think that's fine.",
            "timestamp": "00:03:27"
        },
        {
            "speaker": {
                "display_name": "Will Watters",
                "matched_calendar_invitee_email": "will.watters@metronome.com"
            },
            "text": "I think as long as we can, and you've been great and responsive via Slack.",
            "timestamp": "00:03:28"
        },
        {
            "speaker": {
                "display_name": "Will Watters",
                "matched_calendar_invitee_email": "will.watters@metronome.com"
            },
            "text": "I think that's totally fine.",
            "timestamp": "00:03:32"
        },
        {
            "speaker": {
                "display_name": "Katya Luscomb",
                "matched_calendar_invitee_email": "katya@growthx.ai"
            },
            "text": "Great.",
            "timestamp": "00:03:35"
        },
        {
            "speaker": {
                "display_name": "Katya Luscomb",
                "matched_calendar_invitee_email": "katya@growthx.ai"
            },
            "text": "Yeah.",
            "timestamp": "00:03:35"
        },
        {
            "speaker": {
                "display_name": "Katya Luscomb",
                "matched_calendar_invitee_email": "katya@growthx.ai"
            },
            "text": "And like, if anything comes up where we need to discuss, like I said, we can always hop back into a meeting one week.",
            "timestamp": "00:03:36"
        },
        {
            "speaker": {
                "display_name": "Katya Luscomb",
                "matched_calendar_invitee_email": "katya@growthx.ai"
            },
            "text": "Just freeze up a little bit of my time and yours and we can dig into smart level stuff each time.",
            "timestamp": "00:03:40"
        },
        {
            "speaker": {
                "display_name": "Will Watters",
                "matched_calendar_invitee_email": "will.watters@metronome.com"
            },
            "text": "No, I think we can probably do things async for a couple of weeks.",
            "timestamp": "00:03:45"
        },
        {
            "speaker": {
                "display_name": "Katya Luscomb",
                "matched_calendar_invitee_email": "katya@growthx.ai"
            },
            "text": "But yeah, if anything comes up, I'll just Slack you and we can hop on a call.",
            "timestamp": "00:03:50"
        },
        {
            "speaker": {
                "display_name": "Katya Luscomb",
                "matched_calendar_invitee_email": "katya@growthx.ai"
            },
            "text": "Perfect.",
            "timestamp": "00:03:55"
        },
        {
            "speaker": {
                "display_name": "Katya Luscomb",
                "matched_calendar_invitee_email": "katya@growthx.ai"
            },
            "text": "Slick.",
            "timestamp": "00:03:56"
        },
        {
            "speaker": {
                "display_name": "Katya Luscomb",
                "matched_calendar_invitee_email": "katya@growthx.ai"
            },
            "text": "So I had shared a lot of this.",
            "timestamp": "00:03:58"
        },
        {
            "speaker": {
                "display_name": "Katya Luscomb",
                "matched_calendar_invitee_email": "katya@growthx.ai"
            },
            "text": "Similar to the update I already shared.",
            "timestamp": "00:04:00"
        },
        {
            "speaker": {
                "display_name": "Will Watters",
                "matched_calendar_invitee_email": "will.watters@metronome.com"
            },
            "text": "So if you don't have any questions about kind of what's coming out of the pipe for you guys, I won't turn on about that too much.",
            "timestamp": "00:04:01"
        },
        {
            "speaker": {
                "display_name": "Katya Luscomb",
                "matched_calendar_invitee_email": "katya@growthx.ai"
            },
            "text": "One thing I did want to, a couple things.",
            "timestamp": "00:04:08"
        },
        {
            "speaker": {
                "display_name": "Katya Luscomb",
                "matched_calendar_invitee_email": "katya@growthx.ai"
            },
            "text": "So early in December, we had talked about Wednesdays giving you the JSON files and new docs.",
            "timestamp": "00:04:12"
        },
        {
            "speaker": {
                "display_name": "Katya Luscomb",
                "matched_calendar_invitee_email": "katya@growthx.ai"
            },
            "text": "I chatted with my content dev team, and it's going to be a little bit helpful if we can split that to Tuesday and Thursday.",
            "timestamp": "00:04:17"
        },
        {
            "speaker": {
                "display_name": "Katya Luscomb",
                "matched_calendar_invitee_email": "katya@growthx.ai"
            },
            "text": "So I wanted to check if it would be better for you guys to get the JSON files on Tuesday or the new Google Docs on Tuesday.",
            "timestamp": "00:04:23"
        },
        {
            "speaker": {
                "display_name": "Will Watters",
                "matched_calendar_invitee_email": "will.watters@metronome.com"
            },
            "text": "So you're saying the JSON files from the previous week?",
            "timestamp": "00:04:33"
        },
        {
            "speaker": {
                "display_name": "Will Watters",
                "matched_calendar_invitee_email": "will.watters@metronome.com"
            },
            "text": "Yeah.",
            "timestamp": "00:04:38"
        },
        {
            "speaker": {
                "display_name": "Will Watters",
                "matched_calendar_invitee_email": "will.watters@metronome.com"
            },
            "text": "And then new Google Docs for review on Thursday?",
            "timestamp": "00:04:39"
        },
        {
            "speaker": {
                "display_name": "Katya Luscomb",
                "matched_calendar_invitee_email": "katya@growthx.ai"
            },
            "text": "Correct.",
            "timestamp": "00:04:45"
        },
        {
            "speaker": {
                "display_name": "Katya Luscomb",
                "matched_calendar_invitee_email": "katya@growthx.ai"
            },
            "text": "So we can give either to you on Tuesday and then the other on Thursday.",
            "timestamp": "00:04:45"
        },
        {
            "speaker": {
                "display_name": "Katya Luscomb",
                "matched_calendar_invitee_email": "katya@growthx.ai"
            },
            "text": "I just didn't know if you wanted more time to publish the JSON files or more time to review the Google Docs.",
            "timestamp": "00:04:50"
        },
        {
            "speaker": {
                "display_name": "Will Watters",
                "matched_calendar_invitee_email": "will.watters@metronome.com"
            },
            "text": "on see",
            "timestamp": "00:04:59"
        },
        {
            "speaker": {
                "display_name": "Will Watters",
                "matched_calendar_invitee_email": "will.watters@metronome.com"
            },
            "text": "Um, so, okay, so that's a good question.",
            "timestamp": "00:05:01"
        },
        {
            "speaker": {
                "display_name": "Will Watters",
                "matched_calendar_invitee_email": "will.watters@metronome.com"
            },
            "text": "So I'll be kind of transparent here.",
            "timestamp": "00:05:04"
        },
        {
            "speaker": {
                "display_name": "Will Watters",
                "matched_calendar_invitee_email": "will.watters@metronome.com"
            },
            "text": "Like, the 10 or so that we had that I reviewed, like, it took a good amount of time to, like, review them because of, in some cases, I would say, like, inaccurate data.",
            "timestamp": "00:05:07"
        },
        {
            "speaker": {
                "display_name": "Will Watters",
                "matched_calendar_invitee_email": "will.watters@metronome.com"
            },
            "text": "There's only a couple of those.",
            "timestamp": "00:05:21"
        },
        {
            "speaker": {
                "display_name": "Will Watters",
                "matched_calendar_invitee_email": "will.watters@metronome.com"
            },
            "text": "But in other cases, just, like, not following the template that we had for the previous 10.",
            "timestamp": "00:05:23"
        },
        {
            "speaker": {
                "display_name": "Will Watters",
                "matched_calendar_invitee_email": "will.watters@metronome.com"
            },
            "text": "And so that admittedly, like, got me, like, a little bit concerned over the holidays when I'm like, okay, this is taking me a lot longer than I thought I would need to do to review.",
            "timestamp": "00:05:28"
        },
        {
            "speaker": {
                "display_name": "Will Watters",
                "matched_calendar_invitee_email": "will.watters@metronome.com"
            },
            "text": "Like, I had to review the full page instead of, like, reviewing the Metronome's take.",
            "timestamp": "00:05:38"
        },
        {
            "speaker": {
                "display_name": "Will Watters",
                "matched_calendar_invitee_email": "will.watters@metronome.com"
            },
            "text": "I hope that we will get better at that.",
            "timestamp": "00:05:43"
        },
        {
            "speaker": {
                "display_name": "Will Watters",
                "matched_calendar_invitee_email": "will.watters@metronome.com"
            },
            "text": "And if we can't get better at that, then I probably won't need as much time to review.",
            "timestamp": "00:05:45"
        },
        {
            "speaker": {
                "display_name": "Will Watters",
                "matched_calendar_invitee_email": "will.watters@metronome.com"
            },
            "text": "And maybe it will be only focused on, like, the Metronome's take part.",
            "timestamp": "00:05:50"
        },
        {
            "speaker": {
                "display_name": "Will Watters",
                "matched_calendar_invitee_email": "will.watters@metronome.com"
            },
            "text": "So that's kind of one more, like, broad statement.",
            "timestamp": "00:05:54"
        },
        {
            "speaker": {
                "display_name": "Will Watters",
                "matched_calendar_invitee_email": "will.watters@metronome.com"
            },
            "text": "Now,",
            "timestamp": "00:05:59"
        },
        {
            "speaker": {
                "display_name": "Will Watters",
                "matched_calendar_invitee_email": "will.watters@metronome.com"
            },
            "text": "I think given that, I probably would lean more towards having more time reviewing the Google Docs versus the JSONs.",
            "timestamp": "00:06:00"
        },
        {
            "speaker": {
                "display_name": "Will Watters",
                "matched_calendar_invitee_email": "will.watters@metronome.com"
            },
            "text": "And there will be hiccups.",
            "timestamp": "00:06:09"
        },
        {
            "speaker": {
                "display_name": "Will Watters",
                "matched_calendar_invitee_email": "will.watters@metronome.com"
            },
            "text": "It happens, so I'm not that worried about it.",
            "timestamp": "00:06:11"
        },
        {
            "speaker": {
                "display_name": "Will Watters",
                "matched_calendar_invitee_email": "will.watters@metronome.com"
            },
            "text": "But I would prefer to maybe have the Google Docs sooner for review, and I can try and prioritize that, getting those back to you quickly in case there's some back and forth, and then moving into the JSON file.",
            "timestamp": "00:06:14"
        },
        {
            "speaker": {
                "display_name": "Will Watters",
                "matched_calendar_invitee_email": "will.watters@metronome.com"
            },
            "text": "So I guess that would be, like, Google Docs Tuesday, JSON files Thursday, or something.",
            "timestamp": "00:06:27"
        },
        {
            "speaker": {
                "display_name": "Will Watters",
                "matched_calendar_invitee_email": "will.watters@metronome.com"
            },
            "text": "I don't know.",
            "timestamp": "00:06:32"
        },
        {
            "speaker": {
                "display_name": "Will Watters",
                "matched_calendar_invitee_email": "will.watters@metronome.com"
            },
            "text": "You tell me how that works.",
            "timestamp": "00:06:32"
        },
        {
            "speaker": {
                "display_name": "Katya Luscomb",
                "matched_calendar_invitee_email": "katya@growthx.ai"
            },
            "text": "Yeah, that was kind of how that split was working out in my brain, too.",
            "timestamp": "00:06:34"
        },
        {
            "speaker": {
                "display_name": "Katya Luscomb",
                "matched_calendar_invitee_email": "katya@growthx.ai"
            },
            "text": "I did escalate those issues that you had flagged with the template for my team, and we dug into that a little bit more today.",
            "timestamp": "00:06:38"
        },
        {
            "speaker": {
                "display_name": "Katya Luscomb",
                "matched_calendar_invitee_email": "katya@growthx.ai"
            },
            "text": "I think part of it was developing 10 different articles.",
            "timestamp": "00:06:45"
        },
        {
            "speaker": {
                "display_name": "Katya Luscomb",
                "matched_calendar_invitee_email": "katya@growthx.ai"
            },
            "text": "I know there's a few that slipped through that had the, like, common concerns that we had talked about removing and things.",
            "timestamp": "00:06:48"
        },
        {
            "speaker": {
                "display_name": "Katya Luscomb",
                "matched_calendar_invitee_email": "katya@growthx.ai"
            },
            "text": "So definitely escalated that high priority for us to fix that for you guys, because I don't want you to feel",
            "timestamp": "00:06:54"
        },
        {
            "speaker": {
                "display_name": "Katya Luscomb",
                "matched_calendar_invitee_email": "katya@growthx.ai"
            },
            "text": "Like you need to go line by line through, especially with SEO stuff.",
            "timestamp": "00:07:00"
        },
        {
            "speaker": {
                "display_name": "Will Watters",
                "matched_calendar_invitee_email": "will.watters@metronome.com"
            },
            "text": "Some of it's complex, right?",
            "timestamp": "00:07:04"
        },
        {
            "speaker": {
                "display_name": "Will Watters",
                "matched_calendar_invitee_email": "will.watters@metronome.com"
            },
            "text": "It's like, I'm understanding of that.",
            "timestamp": "00:07:05"
        },
        {
            "speaker": {
                "display_name": "Will Watters",
                "matched_calendar_invitee_email": "will.watters@metronome.com"
            },
            "text": "I think, again, like when I, my alarm bells start ringing when I'm like, okay, we'll discuss this and it's still kind of happening.",
            "timestamp": "00:07:07"
        },
        {
            "speaker": {
                "display_name": "Will Watters",
                "matched_calendar_invitee_email": "will.watters@metronome.com"
            },
            "text": "But it's all good.",
            "timestamp": "00:07:14"
        },
        {
            "speaker": {
                "display_name": "Will Watters",
                "matched_calendar_invitee_email": "will.watters@metronome.com"
            },
            "text": "And like even one thing that I've also been learning myself to be totally candid in the last three months is it's just like, if we are going to separate like an API versus like a consumer product page, like we need to have a level of consistency.",
            "timestamp": "00:07:16"
        },
        {
            "speaker": {
                "display_name": "Katya Luscomb",
                "matched_calendar_invitee_email": "katya@growthx.ai"
            },
            "text": "And like, and there's nuance.",
            "timestamp": "00:07:30"
        },
        {
            "speaker": {
                "display_name": "Will Watters",
                "matched_calendar_invitee_email": "will.watters@metronome.com"
            },
            "text": "So like 11 labs is an example is one that actually has a consumer developer and an API product.",
            "timestamp": "00:07:33"
        },
        {
            "speaker": {
                "display_name": "Will Watters",
                "matched_calendar_invitee_email": "will.watters@metronome.com"
            },
            "text": "However, like they actually have a really interesting model where they actually, they have the same price points for each one of their packages.",
            "timestamp": "00:07:40"
        },
        {
            "speaker": {
                "display_name": "Will Watters",
                "matched_calendar_invitee_email": "will.watters@metronome.com"
            },
            "text": "So it's like, does that make sense having two pages?",
            "timestamp": "00:07:46"
        },
        {
            "speaker": {
                "display_name": "Will Watters",
                "matched_calendar_invitee_email": "will.watters@metronome.com"
            },
            "text": "So like there, there is nuance there and I'm like, I definitely can recognize that.",
            "timestamp": "00:07:49"
        },
        {
            "speaker": {
                "display_name": "Will Watters",
                "matched_calendar_invitee_email": "will.watters@metronome.com"
            },
            "text": "But, I would maybe just ask you and the team to like, when we look at these.",
            "timestamp": "00:07:53"
        },
        {
            "speaker": {
                "display_name": "Will Watters",
                "matched_calendar_invitee_email": "will.watters@metronome.com"
            },
            "text": "let's let's say, say,",
            "timestamp": "00:07:59"
        },
        {
            "speaker": {
                "display_name": "Will Watters",
                "matched_calendar_invitee_email": "will.watters@metronome.com"
            },
            "text": "Just do that type of analysis and maybe just make sure that we have an understanding of why we're not promoting one page versus the other.",
            "timestamp": "00:08:00"
        },
        {
            "speaker": {
                "display_name": "Will Watters",
                "matched_calendar_invitee_email": "will.watters@metronome.com"
            },
            "text": "And again, I can help be helpful and like go through some of them, but it might be easier for you guys to try and catch those before we get them into Google Docs.",
            "timestamp": "00:08:08"
        },
        {
            "speaker": {
                "display_name": "Katya Luscomb",
                "matched_calendar_invitee_email": "katya@growthx.ai"
            },
            "text": "Totally.",
            "timestamp": "00:08:17"
        },
        {
            "speaker": {
                "display_name": "Katya Luscomb",
                "matched_calendar_invitee_email": "katya@growthx.ai"
            },
            "text": "And that was one thing that I had also escalated with my team.",
            "timestamp": "00:08:18"
        },
        {
            "speaker": {
                "display_name": "Katya Luscomb",
                "matched_calendar_invitee_email": "katya@growthx.ai"
            },
            "text": "And I noticed you had called out like XAI had an API page and things that slipped through.",
            "timestamp": "00:08:21"
        },
        {
            "speaker": {
                "display_name": "Katya Luscomb",
                "matched_calendar_invitee_email": "katya@growthx.ai"
            },
            "text": "And so in our content calendar that I put together, I'm having my team go through each of those and confirm that they are actually a singular article.",
            "timestamp": "00:08:27"
        },
        {
            "speaker": {
                "display_name": "Katya Luscomb",
                "matched_calendar_invitee_email": "katya@growthx.ai"
            },
            "text": "Or if they need a separate page to split that out so that that is accurately reflected before we even develop the content.",
            "timestamp": "00:08:36"
        },
        {
            "speaker": {
                "display_name": "Katya Luscomb",
                "matched_calendar_invitee_email": "katya@growthx.ai"
            },
            "text": "And yeah, if there are some where, you know, we think it makes sense to have two, but we want to check with you, I'll raise that for you and we can chat.",
            "timestamp": "00:08:43"
        },
        {
            "speaker": {
                "display_name": "Will Watters",
                "matched_calendar_invitee_email": "will.watters@metronome.com"
            },
            "text": "Yeah, just shoot me Slack and I'll like do a little bit of an investigation.",
            "timestamp": "00:08:50"
        },
        {
            "speaker": {
                "display_name": "Will Watters",
                "matched_calendar_invitee_email": "will.watters@metronome.com"
            },
            "text": "Again, think, yeah, so I think that's probably the big thing that I've noticed so far, but.",
            "timestamp": "00:08:53"
        },
        {
            "speaker": {
                "display_name": "Will Watters",
                "matched_calendar_invitee_email": "will.watters@metronome.com"
            },
            "text": "If there's other things that come up, we can kind of take them as is.",
            "timestamp": "00:09:00"
        },
        {
            "speaker": {
                "display_name": "Will Watters",
                "matched_calendar_invitee_email": "will.watters@metronome.com"
            },
            "text": "But it would be helpful, again, if you just do like another, you or the team just does like another quick spot check.",
            "timestamp": "00:09:03"
        },
        {
            "speaker": {
                "display_name": "Will Watters",
                "matched_calendar_invitee_email": "will.watters@metronome.com"
            },
            "text": "Okay, like this is the pricing model or like this is the pricing page and this is how they separate things out.",
            "timestamp": "00:09:10"
        },
        {
            "speaker": {
                "display_name": "Will Watters",
                "matched_calendar_invitee_email": "will.watters@metronome.com"
            },
            "text": "That's usually the best way to find out like consumer product versus like enterprise or like API type product.",
            "timestamp": "00:09:15"
        },
        {
            "speaker": {
                "display_name": "Katya Luscomb",
                "matched_calendar_invitee_email": "katya@growthx.ai"
            },
            "text": "Yeah, makes sense.",
            "timestamp": "00:09:21"
        },
        {
            "speaker": {
                "display_name": "Katya Luscomb",
                "matched_calendar_invitee_email": "katya@growthx.ai"
            },
            "text": "Related to that, kind of within like the JSON format and things that we've established, I just wanted to make sure that I and my team are really clear on the subheader copy that you had mentioned in your recent message.",
            "timestamp": "00:09:24"
        },
        {
            "speaker": {
                "display_name": "Katya Luscomb",
                "matched_calendar_invitee_email": "katya@growthx.ai"
            },
            "text": "So my understanding is it's this little blurb under the title that we would see in the tag and on the article.",
            "timestamp": "00:09:39"
        },
        {
            "speaker": {
                "display_name": "Katya Luscomb",
                "matched_calendar_invitee_email": "katya@growthx.ai"
            },
            "text": "I know in the JSON files that we had sent over, it's captured in that short description element.",
            "timestamp": "00:09:47"
        },
        {
            "speaker": {
                "display_name": "Katya Luscomb",
                "matched_calendar_invitee_email": "katya@growthx.ai"
            },
            "text": "Is there anything else?",
            "timestamp": "00:09:54"
        },
        {
            "speaker": {
                "display_name": "Katya Luscomb",
                "matched_calendar_invitee_email": "katya@growthx.ai"
            },
            "text": "And I know some of those didn't get into the Google Doc, but you mentioned you had been...",
            "timestamp": "00:09:56"
        },
        {
            "speaker": {
                "display_name": "Will Watters",
                "matched_calendar_invitee_email": "will.watters@metronome.com"
            },
            "text": "Adding them manually.",
            "timestamp": "00:10:00"
        },
        {
            "speaker": {
                "display_name": "Katya Luscomb",
                "matched_calendar_invitee_email": "katya@growthx.ai"
            },
            "text": "So I wanted to make sure that we're aligned there.",
            "timestamp": "00:10:01"
        },
        {
            "speaker": {
                "display_name": "Will Watters",
                "matched_calendar_invitee_email": "will.watters@metronome.com"
            },
            "text": "That's, yeah, that's all I was saying is that like, I think for this round, they are all on there.",
            "timestamp": "00:10:05"
        },
        {
            "speaker": {
                "display_name": "Katya Luscomb",
                "matched_calendar_invitee_email": "katya@growthx.ai"
            },
            "text": "So I think we're good.",
            "timestamp": "00:10:11"
        },
        {
            "speaker": {
                "display_name": "Will Watters",
                "matched_calendar_invitee_email": "will.watters@metronome.com"
            },
            "text": "I think it was like the first 10, they weren't on the Google Doc.",
            "timestamp": "00:10:13"
        },
        {
            "speaker": {
                "display_name": "Will Watters",
                "matched_calendar_invitee_email": "will.watters@metronome.com"
            },
            "text": "And so Chris and I had to kind of like manually add them after the fact, which is, again, it's fine.",
            "timestamp": "00:10:18"
        },
        {
            "speaker": {
                "display_name": "Will Watters",
                "matched_calendar_invitee_email": "will.watters@metronome.com"
            },
            "text": "It is what it is.",
            "timestamp": "00:10:25"
        },
        {
            "speaker": {
                "display_name": "Will Watters",
                "matched_calendar_invitee_email": "will.watters@metronome.com"
            },
            "text": "But for this round, yes, I think like they all should have subheaders.",
            "timestamp": "00:10:25"
        },
        {
            "speaker": {
                "display_name": "Katya Luscomb",
                "matched_calendar_invitee_email": "katya@growthx.ai"
            },
            "text": "And I think they were added and I just like edited them.",
            "timestamp": "00:10:30"
        },
        {
            "speaker": {
                "display_name": "Katya Luscomb",
                "matched_calendar_invitee_email": "katya@growthx.ai"
            },
            "text": "So it was more just like calling out, like, let's make sure that we have those in the Google Docs for everyone moving forward.",
            "timestamp": "00:10:32"
        },
        {
            "speaker": {
                "display_name": "Katya Luscomb",
                "matched_calendar_invitee_email": "katya@growthx.ai"
            },
            "text": "Totally.",
            "timestamp": "00:10:38"
        },
        {
            "speaker": {
                "display_name": "Katya Luscomb",
                "matched_calendar_invitee_email": "katya@growthx.ai"
            },
            "text": "Great.",
            "timestamp": "00:10:39"
        },
        {
            "speaker": {
                "display_name": "Katya Luscomb",
                "matched_calendar_invitee_email": "katya@growthx.ai"
            },
            "text": "I just want to make sure there wasn't a bigger piece of that picture that we were missing that you guys needed.",
            "timestamp": "00:10:39"
        },
        {
            "speaker": {
                "display_name": "Will Watters",
                "matched_calendar_invitee_email": "will.watters@metronome.com"
            },
            "text": "Well, no.",
            "timestamp": "00:10:44"
        },
        {
            "speaker": {
                "display_name": "Will Watters",
                "matched_calendar_invitee_email": "will.watters@metronome.com"
            },
            "text": "I mean, I think I noticed that this is like right after we launched them, that there, I think there was a, something happened like on our end where we didn't pull through the subheader.",
            "timestamp": "00:10:45"
        },
        {
            "speaker": {
                "display_name": "Will Watters",
                "matched_calendar_invitee_email": "will.watters@metronome.com"
            },
            "text": "We didn't pull the actual page, but that I think was more.",
            "timestamp": "00:10:55"
        },
        {
            "speaker": {
                "display_name": "Will Watters",
                "matched_calendar_invitee_email": "will.watters@metronome.com"
            },
            "text": "And it just, like, reminded me that, like, okay, we need to make sure that there's consistency within the copy on the Google Doc to the JSON, which, so yeah, it was more just a call based on something else.",
            "timestamp": "00:11:00"
        },
        {
            "speaker": {
                "display_name": "Katya Luscomb",
                "matched_calendar_invitee_email": "katya@growthx.ai"
            },
            "text": "Yeah, that makes sense.",
            "timestamp": "00:11:13"
        },
        {
            "speaker": {
                "display_name": "Katya Luscomb",
                "matched_calendar_invitee_email": "katya@growthx.ai"
            },
            "text": "And I think one of the glitches, I got some time to, like, play with the JSON files.",
            "timestamp": "00:11:13"
        },
        {
            "speaker": {
                "display_name": "Katya Luscomb",
                "matched_calendar_invitee_email": "katya@growthx.ai"
            },
            "text": "I'm not normally as hands-on, but sometimes I jump in.",
            "timestamp": "00:11:17"
        },
        {
            "speaker": {
                "display_name": "Katya Luscomb",
                "matched_calendar_invitee_email": "katya@growthx.ai"
            },
            "text": "And I was playing with some of the JSON conversions and noticing there's some pieces that we need to clean up that I've got my writing team and our eng team working on so that the Google Doc output matches what our JSON converter needs.",
            "timestamp": "00:11:20"
        },
        {
            "speaker": {
                "display_name": "Katya Luscomb",
                "matched_calendar_invitee_email": "katya@growthx.ai"
            },
            "text": "And, like, that, it can get a little bit messy because of how the JSON conversion works.",
            "timestamp": "00:11:37"
        },
        {
            "speaker": {
                "display_name": "Katya Luscomb",
                "matched_calendar_invitee_email": "katya@growthx.ai"
            },
            "text": "But I think we're getting really close to that.",
            "timestamp": "00:11:41"
        },
        {
            "speaker": {
                "display_name": "Katya Luscomb",
                "matched_calendar_invitee_email": "katya@growthx.ai"
            },
            "text": "So long story short, we should be needing less of your time there.",
            "timestamp": "00:11:42"
        },
        {
            "speaker": {
                "display_name": "Katya Luscomb",
                "matched_calendar_invitee_email": "katya@growthx.ai"
            },
            "text": "In terms of other revision patterns, also noticing there's some, like, some word choice things that are getting revised outside of metronome's take, we can definitely do a pass of the feedback that you've given.",
            "timestamp": "00:11:48"
        },
        {
            "speaker": {
                "display_name": "Katya Luscomb",
                "matched_calendar_invitee_email": "katya@growthx.ai"
            },
            "text": "On some of the recent batches to make sure that any like stylistic voice tone changes we're accounting for.",
            "timestamp": "00:12:00"
        },
        {
            "speaker": {
                "display_name": "Katya Luscomb",
                "matched_calendar_invitee_email": "katya@growthx.ai"
            },
            "text": "But if you've got any specific patterns in that realm that are top of mind, that are easy for you to call out, we can also take that and apply it moving forward too.",
            "timestamp": "00:12:07"
        },
        {
            "speaker": {
                "display_name": "Will Watters",
                "matched_calendar_invitee_email": "will.watters@metronome.com"
            },
            "text": "Yeah, I think it's fine.",
            "timestamp": "00:12:17"
        },
        {
            "speaker": {
                "display_name": "Will Watters",
                "matched_calendar_invitee_email": "will.watters@metronome.com"
            },
            "text": "think, again, like I think there's just some nuance like at the top of the pages where we actually talk about like the pricing model, the credit model, and the packaging model.",
            "timestamp": "00:12:18"
        },
        {
            "speaker": {
                "display_name": "Will Watters",
                "matched_calendar_invitee_email": "will.watters@metronome.com"
            },
            "text": "And there is like some blurredness of that, but I am capturing some of those things as well as the categorization in a separate spreadsheet.",
            "timestamp": "00:12:29"
        },
        {
            "speaker": {
                "display_name": "Will Watters",
                "matched_calendar_invitee_email": "will.watters@metronome.com"
            },
            "text": "So I'm working kind of on my end when I do the review to make sure that there's some consistency across like, yeah, just some consistency across those things.",
            "timestamp": "00:12:39"
        },
        {
            "speaker": {
                "display_name": "Will Watters",
                "matched_calendar_invitee_email": "will.watters@metronome.com"
            },
            "text": "And then as far as like the actual copy, like, I think it's like overall fine.",
            "timestamp": "00:12:49"
        },
        {
            "speaker": {
                "display_name": "Will Watters",
                "matched_calendar_invitee_email": "will.watters@metronome.com"
            },
            "text": "I think it's, yeah, I have.",
            "timestamp": "00:12:57"
        },
        {
            "speaker": {
                "display_name": "Will Watters",
                "matched_calendar_invitee_email": "will.watters@metronome.com"
            },
            "text": "I haven't noticed any like fundamental like style and tone things that I would change other than maybe I guess the one thing that I would say would probably be like in like pricing like the pricing analysis or like the product overview sections like maybe being just like a little bit more objective if we will and like kind of calling out like what it Versus like there's some where some wording where it was like a little bit like like there's like a revolutionary model or product.",
            "timestamp": "00:13:00"
        },
        {
            "speaker": {
                "display_name": "Will Watters",
                "matched_calendar_invitee_email": "will.watters@metronome.com"
            },
            "text": "It's like I think that's fine.",
            "timestamp": "00:13:42"
        },
        {
            "speaker": {
                "display_name": "Will Watters",
                "matched_calendar_invitee_email": "will.watters@metronome.com"
            },
            "text": "And maybe that's just like a personal taste.",
            "timestamp": "00:13:44"
        },
        {
            "speaker": {
                "display_name": "Will Watters",
                "matched_calendar_invitee_email": "will.watters@metronome.com"
            },
            "text": "But like I generally would anchor more on like this is what it is.",
            "timestamp": "00:13:46"
        },
        {
            "speaker": {
                "display_name": "Will Watters",
                "matched_calendar_invitee_email": "will.watters@metronome.com"
            },
            "text": "This is what it does.",
            "timestamp": "00:13:51"
        },
        {
            "speaker": {
                "display_name": "Will Watters",
                "matched_calendar_invitee_email": "will.watters@metronome.com"
            },
            "text": "And then like pricing analysis is again like what is it, what it is, what it does.",
            "timestamp": "00:13:52"
        },
        {
            "speaker": {
                "display_name": "Will Watters",
                "matched_calendar_invitee_email": "will.watters@metronome.com"
            },
            "text": "And then like the metronome's take is the opinion.",
            "timestamp": "00:13:56"
        },
        {
            "speaker": {
                "display_name": "Will Watters",
                "matched_calendar_invitee_email": "will.watters@metronome.com"
            },
            "text": "So like...",
            "timestamp": "00:13:59"
        },
        {
            "speaker": {
                "display_name": "Will Watters",
                "matched_calendar_invitee_email": "will.watters@metronome.com"
            },
            "text": "Based upon what this is and what it does, enables X, Y, Z, and that's the benefit to customers.",
            "timestamp": "00:14:00"
        },
        {
            "speaker": {
                "display_name": "Will Watters",
                "matched_calendar_invitee_email": "will.watters@metronome.com"
            },
            "text": "Again, that's how I think of it in my mind.",
            "timestamp": "00:14:06"
        },
        {
            "speaker": {
                "display_name": "Will Watters",
                "matched_calendar_invitee_email": "will.watters@metronome.com"
            },
            "text": "And so maybe that's, I didn't consciously make those edits to the tone, but maybe that's one area to think about.",
            "timestamp": "00:14:09"
        },
        {
            "speaker": {
                "display_name": "Will Watters",
                "matched_calendar_invitee_email": "will.watters@metronome.com"
            },
            "text": "But yeah, otherwise, nothing really comes to mind, I'd say.",
            "timestamp": "00:14:20"
        },
        {
            "speaker": {
                "display_name": "Katya Luscomb",
                "matched_calendar_invitee_email": "katya@growthx.ai"
            },
            "text": "Okay, cool.",
            "timestamp": "00:14:24"
        },
        {
            "speaker": {
                "display_name": "Katya Luscomb",
                "matched_calendar_invitee_email": "katya@growthx.ai"
            },
            "text": "That's helpful.",
            "timestamp": "00:14:25"
        },
        {
            "speaker": {
                "display_name": "Katya Luscomb",
                "matched_calendar_invitee_email": "katya@growthx.ai"
            },
            "text": "And yeah, we, our AI model, like AI models in general tend to be, yeah, overly complementary and promotional.",
            "timestamp": "00:14:25"
        },
        {
            "speaker": {
                "display_name": "Will Watters",
                "matched_calendar_invitee_email": "will.watters@metronome.com"
            },
            "text": "Yeah, it happens with LLMs, right?",
            "timestamp": "00:14:32"
        },
        {
            "speaker": {
                "display_name": "Will Watters",
                "matched_calendar_invitee_email": "will.watters@metronome.com"
            },
            "text": "It's like, so that's probably more of one thing just, yeah.",
            "timestamp": "00:14:33"
        },
        {
            "speaker": {
                "display_name": "Will Watters",
                "matched_calendar_invitee_email": "will.watters@metronome.com"
            },
            "text": "So maybe that's one thing to just keep in mind is like, yeah, is the model being a little bit too complementary or too effusive in some ways?",
            "timestamp": "00:14:38"
        },
        {
            "speaker": {
                "display_name": "Katya Luscomb",
                "matched_calendar_invitee_email": "katya@growthx.ai"
            },
            "text": "Yeah, that makes sense.",
            "timestamp": "00:14:48"
        },
        {
            "speaker": {
                "display_name": "Katya Luscomb",
                "matched_calendar_invitee_email": "katya@growthx.ai"
            },
            "text": "It's a good shout.",
            "timestamp": "00:14:50"
        },
        {
            "speaker": {
                "display_name": "Katya Luscomb",
                "matched_calendar_invitee_email": "katya@growthx.ai"
            },
            "text": "Any other pieces that are top of mind for you, like quality concerns or...",
            "timestamp": "00:14:53"
        },
        {
            "speaker": {
                "display_name": "Katya Luscomb",
                "matched_calendar_invitee_email": "katya@growthx.ai"
            },
            "text": "Things that you want to talk about before I jump into the last couple pieces?",
            "timestamp": "00:15:00"
        },
        {
            "speaker": {
                "display_name": "Will Watters",
                "matched_calendar_invitee_email": "will.watters@metronome.com"
            },
            "text": "No, I think we're good for now.",
            "timestamp": "00:15:04"
        },
        {
            "speaker": {
                "display_name": "Katya Luscomb",
                "matched_calendar_invitee_email": "katya@growthx.ai"
            },
            "text": "Cool.",
            "timestamp": "00:15:06"
        },
        {
            "speaker": {
                "display_name": "Katya Luscomb",
                "matched_calendar_invitee_email": "katya@growthx.ai"
            },
            "text": "I wanted to flag we are looking at scaling production because this is kind of a hybrid between PSEO and editorial with the Metronome's Take piece.",
            "timestamp": "00:15:08"
        },
        {
            "speaker": {
                "display_name": "Katya Luscomb",
                "matched_calendar_invitee_email": "katya@growthx.ai"
            },
            "text": "So this week we're looking at scaling to six.",
            "timestamp": "00:15:15"
        },
        {
            "speaker": {
                "display_name": "Katya Luscomb",
                "matched_calendar_invitee_email": "katya@growthx.ai"
            },
            "text": "I wanted to gauge your comfort level one because I know you're still reviewing a lot of these as we finalize that alignment.",
            "timestamp": "00:15:17"
        },
        {
            "speaker": {
                "display_name": "Katya Luscomb",
                "matched_calendar_invitee_email": "katya@growthx.ai"
            },
            "text": "Long-term scaling, I'm sort of envisioning hitting somewhere between like six to eight pieces a week.",
            "timestamp": "00:15:25"
        },
        {
            "speaker": {
                "display_name": "Katya Luscomb",
                "matched_calendar_invitee_email": "katya@growthx.ai"
            },
            "text": "So I wanted to gauge your comfort with getting six moving forward for the next couple of weeks and then we can continue to scale from there.",
            "timestamp": "00:15:31"
        },
        {
            "speaker": {
                "display_name": "Will Watters",
                "matched_calendar_invitee_email": "will.watters@metronome.com"
            },
            "text": "Yeah.",
            "timestamp": "00:15:38"
        },
        {
            "speaker": {
                "display_name": "Will Watters",
                "matched_calendar_invitee_email": "will.watters@metronome.com"
            },
            "text": "Yeah, I mean, that's totally fine by me.",
            "timestamp": "00:15:39"
        },
        {
            "speaker": {
                "display_name": "Will Watters",
                "matched_calendar_invitee_email": "will.watters@metronome.com"
            },
            "text": "Again, I think our \u2013 I'm all for scale.",
            "timestamp": "00:15:41"
        },
        {
            "speaker": {
                "display_name": "Will Watters",
                "matched_calendar_invitee_email": "will.watters@metronome.com"
            },
            "text": "I think I just want to make sure like the \u2013 I'm like the quality control piece of the operation.",
            "timestamp": "00:15:47"
        },
        {
            "speaker": {
                "display_name": "Will Watters",
                "matched_calendar_invitee_email": "will.watters@metronome.com"
            },
            "text": "So I want to make sure that there's a high level of quality.",
            "timestamp": "00:15:52"
        },
        {
            "speaker": {
                "display_name": "Will Watters",
                "matched_calendar_invitee_email": "will.watters@metronome.com"
            },
            "text": "And if there is, then we can go to six.",
            "timestamp": "00:15:56"
        },
        {
            "speaker": {
                "display_name": "Will Watters",
                "matched_calendar_invitee_email": "will.watters@metronome.com"
            },
            "text": "It's amazing.",
            "timestamp": "00:15:58"
        },
        {
            "speaker": {
                "display_name": "Will Watters",
                "matched_calendar_invitee_email": "will.watters@metronome.com"
            },
            "text": "Like I should have",
            "timestamp": "00:15:59"
        },
        {
            "speaker": {
                "display_name": "Will Watters",
                "matched_calendar_invitee_email": "will.watters@metronome.com"
            },
            "text": "We again, feasibly to review more as we get better and there's a higher quality on the first draft, less edits and revisions.",
            "timestamp": "00:16:00"
        },
        {
            "speaker": {
                "display_name": "Will Watters",
                "matched_calendar_invitee_email": "will.watters@metronome.com"
            },
            "text": "So I'm fine with that.",
            "timestamp": "00:16:10"
        },
        {
            "speaker": {
                "display_name": "Will Watters",
                "matched_calendar_invitee_email": "will.watters@metronome.com"
            },
            "text": "But I think if we have this conversation in two weeks and it's like I'm still spending the same amount of time reviewing, I'm probably not going to want to go to more than Fathom.",
            "timestamp": "00:16:13"
        },
        {
            "speaker": {
                "display_name": "Katya Luscomb",
                "matched_calendar_invitee_email": "katya@growthx.ai"
            },
            "text": "Totally.",
            "timestamp": "00:16:23"
        },
        {
            "speaker": {
                "display_name": "Katya Luscomb",
                "matched_calendar_invitee_email": "katya@growthx.ai"
            },
            "text": "Yeah, that makes sense.",
            "timestamp": "00:16:24"
        },
        {
            "speaker": {
                "display_name": "Katya Luscomb",
                "matched_calendar_invitee_email": "katya@growthx.ai"
            },
            "text": "So I've got six in the queue for this week.",
            "timestamp": "00:16:26"
        },
        {
            "speaker": {
                "display_name": "Katya Luscomb",
                "matched_calendar_invitee_email": "katya@growthx.ai"
            },
            "text": "If for whatever reason you can only review five, like totally fine.",
            "timestamp": "00:16:30"
        },
        {
            "speaker": {
                "display_name": "Katya Luscomb",
                "matched_calendar_invitee_email": "katya@growthx.ai"
            },
            "text": "We can just like pass a piece on to the next week.",
            "timestamp": "00:16:33"
        },
        {
            "speaker": {
                "display_name": "Katya Luscomb",
                "matched_calendar_invitee_email": "katya@growthx.ai"
            },
            "text": "And then, yeah, we'll sort of we'll hang at six for now and see and then we can reevaluate like early next week or in a couple weeks.",
            "timestamp": "00:16:38"
        },
        {
            "speaker": {
                "display_name": "Will Watters",
                "matched_calendar_invitee_email": "will.watters@metronome.com"
            },
            "text": "Okay.",
            "timestamp": "00:16:46"
        },
        {
            "speaker": {
                "display_name": "Will Watters",
                "matched_calendar_invitee_email": "will.watters@metronome.com"
            },
            "text": "And what is the ideal timing for you to get those back?",
            "timestamp": "00:16:47"
        },
        {
            "speaker": {
                "display_name": "Katya Luscomb",
                "matched_calendar_invitee_email": "katya@growthx.ai"
            },
            "text": "If we get those back on like Friday, end of day or Monday, so we've got them first thing Monday, it's pretty easy for us to turn around those days.",
            "timestamp": "00:16:51"
        },
        {
            "speaker": {
                "display_name": "Katya Luscomb",
                "matched_calendar_invitee_email": "katya@growthx.ai"
            },
            "text": "Based on files, and have them to you by that Thursday.",
            "timestamp": "00:17:00"
        },
        {
            "speaker": {
                "display_name": "Will Watters",
                "matched_calendar_invitee_email": "will.watters@metronome.com"
            },
            "text": "Okay.",
            "timestamp": "00:17:04"
        },
        {
            "speaker": {
                "display_name": "Will Watters",
                "matched_calendar_invitee_email": "will.watters@metronome.com"
            },
            "text": "And do you have a, where are you going to be submitting the Google Docs?",
            "timestamp": "00:17:06"
        },
        {
            "speaker": {
                "display_name": "Will Watters",
                "matched_calendar_invitee_email": "will.watters@metronome.com"
            },
            "text": "Is it in, we have like a folder in Drive, right?",
            "timestamp": "00:17:15"
        },
        {
            "speaker": {
                "display_name": "Katya Luscomb",
                "matched_calendar_invitee_email": "katya@growthx.ai"
            },
            "text": "Yeah, so there's a folder in Drive, and I will send a message in Slack when like the batch is ready.",
            "timestamp": "00:17:19"
        },
        {
            "speaker": {
                "display_name": "Katya Luscomb",
                "matched_calendar_invitee_email": "katya@growthx.ai"
            },
            "text": "Okay.",
            "timestamp": "00:17:27"
        },
        {
            "speaker": {
                "display_name": "Katya Luscomb",
                "matched_calendar_invitee_email": "katya@growthx.ai"
            },
            "text": "you can also see them, there's a couple links here in this Airtables View section.",
            "timestamp": "00:17:28"
        },
        {
            "speaker": {
                "display_name": "Katya Luscomb",
                "matched_calendar_invitee_email": "katya@growthx.ai"
            },
            "text": "Okay.",
            "timestamp": "00:17:34"
        },
        {
            "speaker": {
                "display_name": "Katya Luscomb",
                "matched_calendar_invitee_email": "katya@growthx.ai"
            },
            "text": "So in this by status view here, yeah, it's got all of those lined up.",
            "timestamp": "00:17:35"
        },
        {
            "speaker": {
                "display_name": "Katya Luscomb",
                "matched_calendar_invitee_email": "katya@growthx.ai"
            },
            "text": "And it will have the Google Doc.",
            "timestamp": "00:17:42"
        },
        {
            "speaker": {
                "display_name": "Katya Luscomb",
                "matched_calendar_invitee_email": "katya@growthx.ai"
            },
            "text": "So like when these are in production, when they're ready for you, your Google Doc will be here in this column.",
            "timestamp": "00:17:44"
        },
        {
            "speaker": {
                "display_name": "Will Watters",
                "matched_calendar_invitee_email": "will.watters@metronome.com"
            },
            "text": "Okay.",
            "timestamp": "00:17:49"
        },
        {
            "speaker": {
                "display_name": "Katya Luscomb",
                "matched_calendar_invitee_email": "katya@growthx.ai"
            },
            "text": "We try to make it as easy as possible if don't have to fish through a bajillion Google folders.",
            "timestamp": "00:17:51"
        },
        {
            "speaker": {
                "display_name": "Will Watters",
                "matched_calendar_invitee_email": "will.watters@metronome.com"
            },
            "text": "Yeah, no problem.",
            "timestamp": "00:17:55"
        },
        {
            "speaker": {
                "display_name": "Will Watters",
                "matched_calendar_invitee_email": "will.watters@metronome.com"
            },
            "text": "Oh, okay.",
            "timestamp": "00:17:57"
        },
        {
            "speaker": {
                "display_name": "Will Watters",
                "matched_calendar_invitee_email": "will.watters@metronome.com"
            },
            "text": "Oh,",
            "timestamp": "00:17:57"
        },
        {
            "speaker": {
                "display_name": "Will Watters",
                "matched_calendar_invitee_email": "will.watters@metronome.com"
            },
            "text": "I'm just, like, making a reminder here.",
            "timestamp": "00:18:01"
        },
        {
            "speaker": {
                "display_name": "Katya Luscomb",
                "matched_calendar_invitee_email": "katya@growthx.ai"
            },
            "text": "Yeah, no worries.",
            "timestamp": "00:18:05"
        },
        {
            "speaker": {
                "display_name": "Will Watters",
                "matched_calendar_invitee_email": "will.watters@metronome.com"
            },
            "text": "Okay.",
            "timestamp": "00:18:07"
        },
        {
            "speaker": {
                "display_name": "Will Watters",
                "matched_calendar_invitee_email": "will.watters@metronome.com"
            },
            "text": "Okay, yeah, so I've blocked some time on Thursday, but I might not get to all of them.",
            "timestamp": "00:18:08"
        },
        {
            "speaker": {
                "display_name": "Will Watters",
                "matched_calendar_invitee_email": "will.watters@metronome.com"
            },
            "text": "So, yeah, I'll say, like, hopefully, like, Monday or Friday morning.",
            "timestamp": "00:18:17"
        },
        {
            "speaker": {
                "display_name": "Katya Luscomb",
                "matched_calendar_invitee_email": "katya@growthx.ai"
            },
            "text": "Well, on Thursday, I think our goal when we set those dates, we usually like to have those over to you by, end of day.",
            "timestamp": "00:18:24"
        },
        {
            "speaker": {
                "display_name": "Katya Luscomb",
                "matched_calendar_invitee_email": "katya@growthx.ai"
            },
            "text": "And so this week, because we've got the 10 JSON files we're converting, this week, we're looking at sending over those 10 JSON by Wednesday, end of day.",
            "timestamp": "00:18:31"
        },
        {
            "speaker": {
                "display_name": "Katya Luscomb",
                "matched_calendar_invitee_email": "katya@growthx.ai"
            },
            "text": "And then by Thursday, end of day, we'll have the new Google Docs, which I realize is a slight delay.",
            "timestamp": "00:18:40"
        },
        {
            "speaker": {
                "display_name": "Katya Luscomb",
                "matched_calendar_invitee_email": "katya@growthx.ai"
            },
            "text": "Okay.",
            "timestamp": "00:18:45"
        },
        {
            "speaker": {
                "display_name": "Katya Luscomb",
                "matched_calendar_invitee_email": "katya@growthx.ai"
            },
            "text": "But it's just because we want to prioritize those 10 pieces to get them published.",
            "timestamp": "00:18:46"
        },
        {
            "speaker": {
                "display_name": "Will Watters",
                "matched_calendar_invitee_email": "will.watters@metronome.com"
            },
            "text": "Okay, no problem.",
            "timestamp": "00:18:49"
        },
        {
            "speaker": {
                "display_name": "Will Watters",
                "matched_calendar_invitee_email": "will.watters@metronome.com"
            },
            "text": "Yeah, just, yeah, if you can just make sure that you Slack me or just, like, Slack the channel.",
            "timestamp": "00:18:52"
        },
        {
            "speaker": {
                "display_name": "Will Watters",
                "matched_calendar_invitee_email": "will.watters@metronome.com"
            },
            "text": "Yeah.",
            "timestamp": "00:18:58"
        },
        {
            "speaker": {
                "display_name": "Katya Luscomb",
                "matched_calendar_invitee_email": "katya@growthx.ai"
            },
            "text": "That'd be helpful.",
            "timestamp": "00:18:59"
        },
        {
            "speaker": {
                "display_name": "Katya Luscomb",
                "matched_calendar_invitee_email": "katya@growthx.ai"
            },
            "text": "Yeah, totally.",
            "timestamp": "00:19:00"
        },
        {
            "speaker": {
                "display_name": "Katya Luscomb",
                "matched_calendar_invitee_email": "katya@growthx.ai"
            },
            "text": "And similar, I think you guys, you let me know when you would run through all the other JSON files, but just as Slack on your end, once you publish the pieces, because we then go through and grab those URLs and we have a Looker dashboard set up for us to start doing some initial reporting, looking at like traffic and general impressions and things and going through like indexing to make sure that all of that's looking kosher.",
            "timestamp": "00:19:01"
        },
        {
            "speaker": {
                "display_name": "Will Watters",
                "matched_calendar_invitee_email": "will.watters@metronome.com"
            },
            "text": "Okay.",
            "timestamp": "00:19:25"
        },
        {
            "speaker": {
                "display_name": "Will Watters",
                "matched_calendar_invitee_email": "will.watters@metronome.com"
            },
            "text": "Yeah, that works for me.",
            "timestamp": "00:19:26"
        },
        {
            "speaker": {
                "display_name": "Katya Luscomb",
                "matched_calendar_invitee_email": "katya@growthx.ai"
            },
            "text": "Awesome.",
            "timestamp": "00:19:30"
        },
        {
            "speaker": {
                "display_name": "Will Watters",
                "matched_calendar_invitee_email": "will.watters@metronome.com"
            },
            "text": "Okay.",
            "timestamp": "00:19:31"
        },
        {
            "speaker": {
                "display_name": "Will Watters",
                "matched_calendar_invitee_email": "will.watters@metronome.com"
            },
            "text": "Yeah.",
            "timestamp": "00:19:32"
        },
        {
            "speaker": {
                "display_name": "Will Watters",
                "matched_calendar_invitee_email": "will.watters@metronome.com"
            },
            "text": "All right.",
            "timestamp": "00:19:32"
        },
        {
            "speaker": {
                "display_name": "Will Watters",
                "matched_calendar_invitee_email": "will.watters@metronome.com"
            },
            "text": "Yeah, that should work.",
            "timestamp": "00:19:33"
        },
        {
            "speaker": {
                "display_name": "Katya Luscomb",
                "matched_calendar_invitee_email": "katya@growthx.ai"
            },
            "text": "And then otherwise, I know you said that you have a spreadsheet in the works for some of the, like that top level pricing and categorization.",
            "timestamp": "00:19:35"
        },
        {
            "speaker": {
                "display_name": "Katya Luscomb",
                "matched_calendar_invitee_email": "katya@growthx.ai"
            },
            "text": "At any point when you're ready to share that, we're happy to take it and we can start to figure out the best way for us to implement.",
            "timestamp": "00:19:46"
        },
        {
            "speaker": {
                "display_name": "Katya Luscomb",
                "matched_calendar_invitee_email": "katya@growthx.ai"
            },
            "text": "But it's like putting the category at the top of the Google doc.",
            "timestamp": "00:19:52"
        },
        {
            "speaker": {
                "display_name": "Katya Luscomb",
                "matched_calendar_invitee_email": "katya@growthx.ai"
            },
            "text": "And if that needs to be in the JSON file somewhere, I'm not sure how you guys are handling categorization.",
            "timestamp": "00:19:55"
        },
        {
            "speaker": {
                "display_name": "Will Watters",
                "matched_calendar_invitee_email": "will.watters@metronome.com"
            },
            "text": "At this point.",
            "timestamp": "00:20:00"
        },
        {
            "speaker": {
                "display_name": "Will Watters",
                "matched_calendar_invitee_email": "will.watters@metronome.com"
            },
            "text": "Sorry, can you say that again?",
            "timestamp": "00:20:04"
        },
        {
            "speaker": {
                "display_name": "Katya Luscomb",
                "matched_calendar_invitee_email": "katya@growthx.ai"
            },
            "text": "Yeah, no worries.",
            "timestamp": "00:20:07"
        },
        {
            "speaker": {
                "display_name": "Katya Luscomb",
                "matched_calendar_invitee_email": "katya@growthx.ai"
            },
            "text": "We had talked a few weeks ago that you guys are still deciding on how you want to add tags or categories to each piece of content.",
            "timestamp": "00:20:08"
        },
        {
            "speaker": {
                "display_name": "Katya Luscomb",
                "matched_calendar_invitee_email": "katya@growthx.ai"
            },
            "text": "We have not been tagging them yet because we didn't have that breakdown from you all.",
            "timestamp": "00:20:18"
        },
        {
            "speaker": {
                "display_name": "Katya Luscomb",
                "matched_calendar_invitee_email": "katya@growthx.ai"
            },
            "text": "I know with the 10 pieces that were published, I saw some tags on them.",
            "timestamp": "00:20:23"
        },
        {
            "speaker": {
                "display_name": "Will Watters",
                "matched_calendar_invitee_email": "will.watters@metronome.com"
            },
            "text": "Yeah, so let's do this another, let's do this like this week's round and see how it breaks down because it's kind of like what I was saying before where there's nuance.",
            "timestamp": "00:20:27"
        },
        {
            "speaker": {
                "display_name": "Will Watters",
                "matched_calendar_invitee_email": "will.watters@metronome.com"
            },
            "text": "It's not been like the easiest way to like bucket everything.",
            "timestamp": "00:20:43"
        },
        {
            "speaker": {
                "display_name": "Will Watters",
                "matched_calendar_invitee_email": "will.watters@metronome.com"
            },
            "text": "So let me take another look at this week and then maybe I can share this spreadsheet with you and we can go a little bit deeper.",
            "timestamp": "00:20:51"
        },
        {
            "speaker": {
                "display_name": "Will Watters",
                "matched_calendar_invitee_email": "will.watters@metronome.com"
            },
            "text": "Sure.",
            "timestamp": "00:20:59"
        },
        {
            "speaker": {
                "display_name": "Will Watters",
                "matched_calendar_invitee_email": "will.watters@metronome.com"
            },
            "text": "Okay.",
            "timestamp": "00:20:59"
        },
        {
            "speaker": {
                "display_name": "Will Watters",
                "matched_calendar_invitee_email": "will.watters@metronome.com"
            },
            "text": "Because, again, it's like, you know, we have, we could have multiple pages for multiple companies, and then on top of that, like, they maybe have some nuance in how they price one product versus the next.",
            "timestamp": "00:21:00"
        },
        {
            "speaker": {
                "display_name": "Will Watters",
                "matched_calendar_invitee_email": "will.watters@metronome.com"
            },
            "text": "So, but I haven't looked at it in a couple weeks, but I sent it to Chris to, like, kind of, like, test this out and see how it fits.",
            "timestamp": "00:21:12"
        },
        {
            "speaker": {
                "display_name": "Will Watters",
                "matched_calendar_invitee_email": "will.watters@metronome.com"
            },
            "text": "I think it looks okay for right now, but for this round, I'll take another look and see where these fit, and then, you we can go from there.",
            "timestamp": "00:21:21"
        },
        {
            "speaker": {
                "display_name": "Katya Luscomb",
                "matched_calendar_invitee_email": "katya@growthx.ai"
            },
            "text": "Perfect.",
            "timestamp": "00:21:30"
        },
        {
            "speaker": {
                "display_name": "Katya Luscomb",
                "matched_calendar_invitee_email": "katya@growthx.ai"
            },
            "text": "Yeah, makes sense.",
            "timestamp": "00:21:30"
        },
        {
            "speaker": {
                "display_name": "Katya Luscomb",
                "matched_calendar_invitee_email": "katya@growthx.ai"
            },
            "text": "Like you said, I know there's, there's a lot of nuance between all of this, and much as it's nice to break things down into clean buckets, it doesn't always happen that way.",
            "timestamp": "00:21:32"
        },
        {
            "speaker": {
                "display_name": "Will Watters",
                "matched_calendar_invitee_email": "will.watters@metronome.com"
            },
            "text": "Yeah, yeah, and there's, like, yeah, so I'll leave it at that, yeah.",
            "timestamp": "00:21:39"
        },
        {
            "speaker": {
                "display_name": "Katya Luscomb",
                "matched_calendar_invitee_email": "katya@growthx.ai"
            },
            "text": "Cool.",
            "timestamp": "00:21:43"
        },
        {
            "speaker": {
                "display_name": "Katya Luscomb",
                "matched_calendar_invitee_email": "katya@growthx.ai"
            },
            "text": "And we already talked about starting with ByLadyChats, I just put basically what that schedule would look like here, and I'll update our content, our calendar invite as well, so that that's clear for everyone.",
            "timestamp": "00:21:44"
        },
        {
            "speaker": {
                "display_name": "Katya Luscomb",
                "matched_calendar_invitee_email": "katya@growthx.ai"
            },
            "text": "So, that's all I had for this week.",
            "timestamp": "00:21:55"
        },
        {
            "speaker": {
                "display_name": "Katya Luscomb",
                "matched_calendar_invitee_email": "katya@growthx.ai"
            },
            "text": "Anything else on top?",
            "timestamp": "00:21:58"
        },
        {
            "speaker": {
                "display_name": "Will Watters",
                "matched_calendar_invitee_email": "will.watters@metronome.com"
            },
            "text": "I think that's good.",
            "timestamp": "00:22:00"
        },
        {
            "speaker": {
                "display_name": "Will Watters",
                "matched_calendar_invitee_email": "will.watters@metronome.com"
            },
            "text": "mean, obviously like want to continue to push these out now that we've got the first 10 or so up.",
            "timestamp": "00:22:03"
        },
        {
            "speaker": {
                "display_name": "Will Watters",
                "matched_calendar_invitee_email": "will.watters@metronome.com"
            },
            "text": "So, you know, just keep cracking away.",
            "timestamp": "00:22:08"
        },
        {
            "speaker": {
                "display_name": "Katya Luscomb",
                "matched_calendar_invitee_email": "katya@growthx.ai"
            },
            "text": "Great.",
            "timestamp": "00:22:11"
        },
        {
            "speaker": {
                "display_name": "Katya Luscomb",
                "matched_calendar_invitee_email": "katya@growthx.ai"
            },
            "text": "Yeah.",
            "timestamp": "00:22:11"
        },
        {
            "speaker": {
                "display_name": "Katya Luscomb",
                "matched_calendar_invitee_email": "katya@growthx.ai"
            },
            "text": "It was excited to see them go live.",
            "timestamp": "00:22:12"
        },
        {
            "speaker": {
                "display_name": "Katya Luscomb",
                "matched_calendar_invitee_email": "katya@growthx.ai"
            },
            "text": "Cool.",
            "timestamp": "00:22:15"
        },
        {
            "speaker": {
                "display_name": "Will Watters",
                "matched_calendar_invitee_email": "will.watters@metronome.com"
            },
            "text": "Awesome.",
            "timestamp": "00:22:15"
        },
        {
            "speaker": {
                "display_name": "Will Watters",
                "matched_calendar_invitee_email": "will.watters@metronome.com"
            },
            "text": "Awesome.",
            "timestamp": "00:22:16"
        },
        {
            "speaker": {
                "display_name": "Will Watters",
                "matched_calendar_invitee_email": "will.watters@metronome.com"
            },
            "text": "We'll appreciate it.",
            "timestamp": "00:22:16"
        },
        {
            "speaker": {
                "display_name": "Will Watters",
                "matched_calendar_invitee_email": "will.watters@metronome.com"
            },
            "text": "And we'll talk to you in a couple of weeks.",
            "timestamp": "00:22:17"
        },
        {
            "speaker": {
                "display_name": "Katya Luscomb",
                "matched_calendar_invitee_email": "katya@growthx.ai"
            },
            "text": "Sounds good.",
            "timestamp": "00:22:19"
        },
        {
            "speaker": {
                "display_name": "Will Watters",
                "matched_calendar_invitee_email": "will.watters@metronome.com"
            },
            "text": "Have a good one.",
            "timestamp": "00:22:19"
        },
        {
            "speaker": {
                "display_name": "Will Watters",
                "matched_calendar_invitee_email": "will.watters@metronome.com"
            },
            "text": "You too.",
            "timestamp": "00:22:20"
        },
        {
            "speaker": {
                "display_name": "Will Watters",
                "matched_calendar_invitee_email": "will.watters@metronome.com"
            },
            "text": "See ya.",
            "timestamp": "00:22:21"
        },
        {
            "speaker": {
                "display_name": "Will Watters",
                "matched_calendar_invitee_email": "will.watters@metronome.com"
            },
            "text": "Bye.",
            "timestamp": "00:22:21"
        }
    ],
    "transcript_language": "en",
    "default_summary": {
        "template_name": "General",
        "markdown_formatted": "## Meeting Purpose\n\n[Align on content workflow, quality, and production scale.](https://fathom.video/share/_T2SKdVKb_7PNaZNkkgj1Y4HL49Hisd1?tab=summary&timestamp=180.0)\n\n## Key Takeaways\n\n  - [**New Workflow:** Google Docs will be delivered Tuesdays for review, with JSON files following on Thursdays. This gives Metronome more time for the critical review phase.](https://fathom.video/share/_T2SKdVKb_7PNaZNkkgj1Y4HL49Hisd1?tab=summary&timestamp=252.0)\n  - [**Quality Control:** Metronome's review time is high due to inconsistent templates and inaccurate data. GrowthX is implementing new checks to fix these issues and reduce the review burden.](https://fathom.video/share/_T2SKdVKb_7PNaZNkkgj1Y4HL49Hisd1?tab=summary&timestamp=304.0)\n  - [**Production Scale:** Production will increase to 6 articles/week, contingent on quality improving. If review time doesn't decrease, the rate will be capped at 5.](https://fathom.video/share/_T2SKdVKb_7PNaZNkkgj1Y4HL49Hisd1?tab=summary&timestamp=908.0)\n  - [**Tone & Categorization:** Content analysis sections must be objective (\"what it is\"), reserving opinion for the \"Metronome's Take.\" A new categorization system is in development to provide consistency.](https://fathom.video/share/_T2SKdVKb_7PNaZNkkgj1Y4HL49Hisd1?tab=summary&timestamp=769.0)\n\n## Topics\n\n### Content Quality & Review Process\n\n  - [**Problem:** Metronome's review time is excessive because articles often deviate from the agreed-upon template and contain inaccurate data.](https://fathom.video/share/_T2SKdVKb_7PNaZNkkgj1Y4HL49Hisd1?tab=summary&timestamp=304.0)\n  - [**Example:** The 11 Labs page incorrectly split a single product into two pages (consumer/API) despite its unified pricing model.](https://fathom.video/share/_T2SKdVKb_7PNaZNkkgj1Y4HL49Hisd1?tab=summary&timestamp=453.0)\n  - [**Solution:** GrowthX will implement new checks to ensure:](https://fathom.video/share/_T2SKdVKb_7PNaZNkkgj1Y4HL49Hisd1?tab=summary&timestamp=498.0)\n      - [Singular articles are not split into multiple pages.](https://fathom.video/share/_T2SKdVKb_7PNaZNkkgj1Y4HL49Hisd1?tab=summary&timestamp=498.0)\n      - [Subheaders are included in Google Docs to eliminate manual additions.](https://fathom.video/share/_T2SKdVKb_7PNaZNkkgj1Y4HL49Hisd1?tab=summary&timestamp=564.0)\n      - [JSON conversion is accurate to prevent data mismatches.](https://fathom.video/share/_T2SKdVKb_7PNaZNkkgj1Y4HL49Hisd1?tab=summary&timestamp=673.0)\n\n### New Workflow & Schedule\n\n  - [**Rationale:** To give Metronome more time for the critical review phase, the delivery schedule is being split.](https://fathom.video/share/_T2SKdVKb_7PNaZNkkgj1Y4HL49Hisd1?tab=summary&timestamp=252.0)\n  - [**New Cadence:**](https://fathom.video/share/_T2SKdVKb_7PNaZNkkgj1Y4HL49Hisd1?tab=summary&timestamp=252.0)\n      - [**Tuesdays:** New Google Docs for review.](https://fathom.video/share/_T2SKdVKb_7PNaZNkkgj1Y4HL49Hisd1?tab=summary&timestamp=252.0)\n      - [**Thursdays:** JSON files for publication.](https://fathom.video/share/_T2SKdVKb_7PNaZNkkgj1Y4HL49Hisd1?tab=summary&timestamp=252.0)\n  - [**This Week's Exception:** The 10 articles from the previous batch will be prioritized for publication.](https://fathom.video/share/_T2SKdVKb_7PNaZNkkgj1Y4HL49Hisd1?tab=summary&timestamp=1104.0)\n      - [**Wed, EOD:** 10 JSON files delivered.](https://fathom.video/share/_T2SKdVKb_7PNaZNkkgj1Y4HL49Hisd1?tab=summary&timestamp=1104.0)\n      - [**Thurs, EOD:** New batch of Google Docs delivered.](https://fathom.video/share/_T2SKdVKb_7PNaZNkkgj1Y4HL49Hisd1?tab=summary&timestamp=1104.0)\n\n### Production Scaling\n\n  - [**Plan:** Increase production from 5 to 6 articles/week.](https://fathom.video/share/_T2SKdVKb_7PNaZNkkgj1Y4HL49Hisd1?tab=summary&timestamp=908.0)\n  - [**Contingency:** The 6-article rate is dependent on quality improvements. If review time remains high, the rate will be capped at 5.](https://fathom.video/share/_T2SKdVKb_7PNaZNkkgj1Y4HL49Hisd1?tab=summary&timestamp=908.0)\n  - [**Review Cadence:** Reviews are due Friday EOD or Monday AM.](https://fathom.video/share/_T2SKdVKb_7PNaZNkkgj1Y4HL49Hisd1?tab=summary&timestamp=1007.0)\n\n### Tone & Categorization\n\n  - [**Tone:** Analysis sections must be objective (\"what it is\"), reserving opinion for the \"Metronome's Take.\" This corrects the AI's tendency for overly promotional language.](https://fathom.video/share/_T2SKdVKb_7PNaZNkkgj1Y4HL49Hisd1?tab=summary&timestamp=769.0)\n  - [**Categorization:** A new system is needed to provide consistency across articles.](https://fathom.video/share/_T2SKdVKb_7PNaZNkkgj1Y4HL49Hisd1?tab=summary&timestamp=1175.0)\n      - [**Challenge:** The system must account for product nuance (e.g., API vs. consumer) and varied pricing models.](https://fathom.video/share/_T2SKdVKb_7PNaZNkkgj1Y4HL49Hisd1?tab=summary&timestamp=1227.0)\n      - [**Status:** Will is developing a spreadsheet to define categories and will share it with GrowthX for implementation.](https://fathom.video/share/_T2SKdVKb_7PNaZNkkgj1Y4HL49Hisd1?tab=summary&timestamp=1175.0)\n\n## Next Steps\n\n  - [**GrowthX:**](https://fathom.video/share/_T2SKdVKb_7PNaZNkkgj1Y4HL49Hisd1?tab=summary&timestamp=1104.0)\n      - [Deliver 10 JSON files by Wed, EOD.](https://fathom.video/share/_T2SKdVKb_7PNaZNkkgj1Y4HL49Hisd1?tab=summary&timestamp=1104.0)\n      - [Deliver new Google Docs by Thurs, EOD.](https://fathom.video/share/_T2SKdVKb_7PNaZNkkgj1Y4HL49Hisd1?tab=summary&timestamp=1104.0)\n      - [Notify Metronome via Slack when docs are ready.](https://fathom.video/share/_T2SKdVKb_7PNaZNkkgj1Y4HL49Hisd1?tab=summary&timestamp=1026.0)\n      - [Update calendar invites for the bi-weekly meeting cadence.](https://fathom.video/share/_T2SKdVKb_7PNaZNkkgj1Y4HL49Hisd1?tab=summary&timestamp=1304.0)\n  - [**Metronome:**](https://fathom.video/share/_T2SKdVKb_7PNaZNkkgj1Y4HL49Hisd1?tab=summary&timestamp=1007.0)\n      - [Review new Google Docs by Fri, EOD or Mon, AM.](https://fathom.video/share/_T2SKdVKb_7PNaZNkkgj1Y4HL49Hisd1?tab=summary&timestamp=1007.0)\n      - [Notify GrowthX via Slack after publishing JSON files.](https://fathom.video/share/_T2SKdVKb_7PNaZNkkgj1Y4HL49Hisd1?tab=summary&timestamp=1141.0)\n      - [Share the categorization spreadsheet with GrowthX for implementation.](https://fathom.video/share/_T2SKdVKb_7PNaZNkkgj1Y4HL49Hisd1?tab=summary&timestamp=1175.0)\n"
    },
    "action_items": [
        {
            "description": "Update recurring invite to bi-weekly starting next week",
            "user_generated": false,
            "completed": false,
            "recording_timestamp": "00:02:59",
            "recording_playback_url": "https://fathom.video/calls/521647680?timestamp=179.9999",
            "assignee": {
                "name": "Katya Luscomb",
                "email": "katya@growthx.ai",
                "team": null
            }
        },
        {
            "description": "Deliver 6 new Google Docs to Will by Jan 8 EOD; Slack channel on delivery",
            "user_generated": false,
            "completed": false,
            "recording_timestamp": "00:18:20",
            "recording_playback_url": "https://fathom.video/calls/521647680?timestamp=1100.9999",
            "assignee": {
                "name": "Katya Luscomb",
                "email": "katya@growthx.ai",
                "team": null
            }
        },
        {
            "description": "Deliver 10 JSONs to Will by Jan 7 EOD; Slack channel on delivery",
            "user_generated": false,
            "completed": false,
            "recording_timestamp": "00:18:20",
            "recording_playback_url": "https://fathom.video/calls/521647680?timestamp=1100.9999",
            "assignee": {
                "name": "Katya Luscomb",
                "email": "katya@growthx.ai",
                "team": null
            }
        },
        {
            "description": "Review this week's batch; share categorization spreadsheet w/ Katya",
            "user_generated": false,
            "completed": false,
            "recording_timestamp": "00:20:16",
            "recording_playback_url": "https://fathom.video/calls/521647680?timestamp=1216.9999",
            "assignee": {
                "name": "Will Watters",
                "email": "will.watters@metronome.com",
                "team": null
            }
        }
    ],
    "calendar_invitees": [
        {
            "name": "mlaflamme@metronome.com",
            "email": "mlaflamme@metronome.com",
            "email_domain": "metronome.com",
            "is_external": true,
            "matched_speaker_display_name": null
        },
        {
            "name": "Will Proctor",
            "email": "c-will.proctor@growthx.ai",
            "email_domain": "growthx.ai",
            "is_external": true,
            "matched_speaker_display_name": null
        },
        {
            "name": "Katya Luscomb",
            "email": "katya@growthx.ai",
            "email_domain": "growthx.ai",
            "is_external": true,
            "matched_speaker_display_name": "Katya Luscomb"
        },
        {
            "name": "will.watters@metronome.com",
            "email": "will.watters@metronome.com",
            "email_domain": "metronome.com",
            "is_external": true,
            "matched_speaker_display_name": "Will Watters"
        },
        {
            "name": "Team GrowthX",
            "email": "team@growthxlabs.com",
            "email_domain": "growthxlabs.com",
            "is_external": false,
            "matched_speaker_display_name": null
        }
    ],
    "recorded_by": {
        "name": "Team GrowthX",
        "email": "team@growthxlabs.com",
        "email_domain": "growthxlabs.com",
        "team": "GrowthX Team"
    },
    "share_url": "https://fathom.video/share/_T2SKdVKb_7PNaZNkkgj1Y4HL49Hisd1",
    "crm_matches": {
        "error": "No CRM connected"
    }
}
